cloudage/__init__.py
cloudage/_version.py
cloudage/cloudage.py
cloudage-0.1.0.dist-info/METADATA
cloudage-0.1.0.dist-info/WHEEL
cloudage-0.1.0.dist-info/entry_points.txt
cloudage-0.1.0.dist-info/top_level.txt
cloudage-0.1.0.dist-info/RECORD
