Metadata-Version: 2.1
Name: cloudage
Version: 0.1.0
Summary: Converts AWS CloudFormation to Graphviz DOT.
Home-page: UNKNOWN
Author: Ross Fenning
Author-email: github@rossfenning.co.uk
License: UNKNOWN
Platform: UNKNOWN
Requires-Dist: setuptools
Provides-Extra: test
Requires-Dist: pytest ; extra == 'test'
Requires-Dist: pytest-pikachu ; extra == 'test'
Requires-Dist: pytest-mypy ; extra == 'test'
